rclone/__init__.py
rclone/base32768.py
rclone/eme.py
rclone/file_cipher.py
rclone/name_cipher.py
rclone/util.py
rclone_crypt-1.2.0.dist-info/LICENSE
rclone_crypt-1.2.0.dist-info/METADATA
rclone_crypt-1.2.0.dist-info/WHEEL
rclone_crypt-1.2.0.dist-info/top_level.txt
rclone_crypt-1.2.0.dist-info/RECORD
