Metadata-Version: 2.2
Name: rclone-crypt
Version: 1.2.0
Summary: Python implementation of encryption/decryption for rclone (crypt storage)
Home-page: https://github.com/Ftbom/rclone_crypt_py
Author: ftbom
Author-email: lz490070@gmail.com
License: MIT
Project-URL: Bug Tracker, https://github.com/Ftbom/rclone_crypt_py/issues
Keywords: rclone,decrypt,encrypt
Classifier: Operating System :: OS Independent
Classifier: Intended Audience :: Developers
Classifier: License :: OSI Approved :: MIT License
Classifier: Programming Language :: Python :: 3
Requires-Python: >=3.8
License-File: LICENSE
Requires-Dist: PyNaCl
Requires-Dist: pycryptodome
Dynamic: author
Dynamic: author-email
Dynamic: classifier
Dynamic: description
Dynamic: description-content-type
Dynamic: home-page
Dynamic: keywords
Dynamic: license
Dynamic: project-url
Dynamic: requires-dist
Dynamic: requires-python
Dynamic: summary
